garf/community/google/merchant/__init__.py
garf/community/google/merchant/api_clients.py
garf/community/google/merchant/exceptions.py
garf/community/google/merchant/query_editor.py
garf/community/google/merchant/report_fetcher.py
garf_merchant_api-1.0.0.dist-info/METADATA
garf_merchant_api-1.0.0.dist-info/WHEEL
garf_merchant_api-1.0.0.dist-info/entry_points.txt
garf_merchant_api-1.0.0.dist-info/top_level.txt
garf_merchant_api-1.0.0.dist-info/RECORD
