Metadata-Version: 2.4
Name: garf-merchant-api
Version: 1.0.0
Summary: Garf implementation for Google Merchant API
Author-email: "Google Inc. (gTech gPS CSE team)" <no-reply@google.com>
License: Apache 2.0
Classifier: Development Status :: 4 - Beta
Classifier: Programming Language :: Python
Requires-Python: >=3.8
Requires-Dist: garf-core
Requires-Dist: garf-io
Requires-Dist: google-shopping-merchant-reports
